fmralign/__init__.py
fmralign/_utils.py
fmralign/_version.py
fmralign/fetch_example_data.py
fmralign/metrics.py
fmralign/alignment/group_alignment.py
fmralign/alignment/pairwise_alignment.py
fmralign/alignment/utils.py
fmralign/alignment/tests/test_group_alignment.py
fmralign/alignment/tests/test_pairwise_alignment.py
fmralign/alignment/tests/test_utils.py
fmralign/embeddings/__init__.py
fmralign/embeddings/connectivity.py
fmralign/embeddings/parcellation.py
fmralign/embeddings/whole_brain.py
fmralign/embeddings/tests/test_connectivity.py
fmralign/embeddings/tests/test_parcellation.py
fmralign/embeddings/tests/test_whole_brain.py
fmralign/methods/__init__.py
fmralign/methods/base.py
fmralign/methods/identity.py
fmralign/methods/ot.py
fmralign/methods/piecewise.py
fmralign/methods/procrustes.py
fmralign/methods/ridge.py
fmralign/methods/srm.py
fmralign/methods/tests/test_base.py
fmralign/methods/tests/test_identity.py
fmralign/methods/tests/test_ot.py
fmralign/methods/tests/test_piecewise.py
fmralign/methods/tests/test_procrustes.py
fmralign/methods/tests/test_ridge.py
fmralign/methods/tests/test_srm.py
fmralign/tests/__init__.py
fmralign/tests/conftest.py
fmralign/tests/test_metrics.py
fmralign/tests/test_utils.py
fmralign/tests/utils.py
fmralign-0.0.4.dist-info/METADATA
fmralign-0.0.4.dist-info/WHEEL
fmralign-0.0.4.dist-info/licenses/AUTHORS.rst
fmralign-0.0.4.dist-info/licenses/LICENSE
fmralign-0.0.4.dist-info/RECORD
