Metadata-Version: 2.4
Name: fmralign
Version: 0.0.4
Summary: Functional alignment for fMRI
Author: Thomas Bazeille, Bertrand Thirion
Author-email: Elizabeth DuPre <emd222@cornell.edu>
License: Copyright (c) 2019, fmralign
License-File: AUTHORS.rst
License-File: LICENSE
Classifier: Programming Language :: Python :: 3
Requires-Python: >=3.9
Requires-Dist: fugw>=0.1.1
Requires-Dist: joblib
Requires-Dist: matplotlib
Requires-Dist: nibabel
Requires-Dist: nilearn>=0.12.0
Requires-Dist: numpy<2
Requires-Dist: pandas
Requires-Dist: pot
Requires-Dist: scikit-learn
Requires-Dist: scipy
Requires-Dist: torch
Provides-Extra: dev
Requires-Dist: coverage; extra == 'dev'
Requires-Dist: furo; extra == 'dev'
Requires-Dist: myst-parser; extra == 'dev'
Requires-Dist: numpydoc; extra == 'dev'
Requires-Dist: pytest-cov; extra == 'dev'
Requires-Dist: pytest>=6.0.0; extra == 'dev'
Requires-Dist: ruamel-yaml; extra == 'dev'
Requires-Dist: ruff; extra == 'dev'
Requires-Dist: sphinx; extra == 'dev'
Requires-Dist: sphinx-copybutton; extra == 'dev'
Requires-Dist: sphinx-design; extra == 'dev'
Requires-Dist: sphinx-gallery; extra == 'dev'
Requires-Dist: sphinxcontrib-bibtex; extra == 'dev'
Requires-Dist: sphinxext-opengraph; extra == 'dev'
Provides-Extra: doc
Requires-Dist: coverage; extra == 'doc'
Requires-Dist: furo; extra == 'doc'
Requires-Dist: myst-parser; extra == 'doc'
Requires-Dist: numpydoc; extra == 'doc'
Requires-Dist: ruamel-yaml; extra == 'doc'
Requires-Dist: sphinx; extra == 'doc'
Requires-Dist: sphinx-copybutton; extra == 'doc'
Requires-Dist: sphinx-design; extra == 'doc'
Requires-Dist: sphinx-gallery; extra == 'doc'
Requires-Dist: sphinxcontrib-bibtex; extra == 'doc'
Requires-Dist: sphinxext-opengraph; extra == 'doc'
Provides-Extra: test
Requires-Dist: coverage; extra == 'test'
Requires-Dist: pytest-cov; extra == 'test'
Requires-Dist: pytest>=6.0.0; extra == 'test'
